auto_ts_ensemble_rupakbob/__init__.py
auto_ts_ensemble_rupakbob/auto_ts_ensemble.py
auto_ts_ensemble-0.0.6.dist-info/LICENSE
auto_ts_ensemble-0.0.6.dist-info/METADATA
auto_ts_ensemble-0.0.6.dist-info/WHEEL
auto_ts_ensemble-0.0.6.dist-info/top_level.txt
auto_ts_ensemble-0.0.6.dist-info/RECORD
